torch_pruning/__init__.py
torch_pruning/_helpers.py
torch_pruning/dependency.py
torch_pruning/load_pruned_model.py
torch_pruning/ops.py
torch_pruning/pruning_utils.py
torch_pruning/serialization.py
torch_pruning/pruner/__init__.py
torch_pruning/pruner/function.py
torch_pruning/pruner/importance.py
torch_pruning/pruner/algorithms/__init__.py
torch_pruning/pruner/algorithms/batchnorm_scale_pruner.py
torch_pruning/pruner/algorithms/group_norm_pruner.py
torch_pruning/pruner/algorithms/growing_reg_pruner.py
torch_pruning/pruner/algorithms/magnitude_based_pruner.py
torch_pruning/pruner/algorithms/metapruner.py
torch_pruning/pruner/algorithms/scheduler.py
torch_pruning/utils/__init__.py
torch_pruning/utils/benchmark.py
torch_pruning/utils/compute_mat_grad.py
torch_pruning/utils/op_counter.py
torch_pruning/utils/utils.py
pruning_aware_training-0.1.0.dist-info/METADATA
pruning_aware_training-0.1.0.dist-info/WHEEL
pruning_aware_training-0.1.0.dist-info/top_level.txt
pruning_aware_training-0.1.0.dist-info/RECORD
