Metadata-Version: 2.4
Name: pruning-aware-training
Version: 0.1.0
Summary: A framework for structured channel pruning in PyTorch
Author: Avraham Raviv
License: MIT
Requires-Python: >=3.8
Requires-Dist: torch>=1.10
Requires-Dist: torchvision
Requires-Dist: numpy
Dynamic: author
Dynamic: license
Dynamic: requires-dist
Dynamic: requires-python
Dynamic: summary
